checkin/__init__.py
checkin/__main__.py
checkin/UI/EditDbDialog.py
checkin/UI/aboutScreen.py
checkin/UI/activeScreen.py
checkin/UI/checkinCalendarScreen.py
checkin/UI/checkinUI.py
checkin/UI/infoScreen.py
checkin/function/databaseFunc.py
checkin/function/logSettings.py
checkin/icons/CheckinIcon.ico
checkin/icons/Info-icon.png
checkin/icons/Py_Logo.png
checkin/icons/__init__.py
checkin/icons/checkin_app_screenshot.png
security-checkin/__main__.py
security-checkin/UI/EditDbDialog.py
security-checkin/UI/aboutScreen.py
security-checkin/UI/activeScreen.py
security-checkin/UI/checkinCalendarScreen.py
security-checkin/UI/checkinUI.py
security-checkin/UI/infoScreen.py
security-checkin/function/databaseFunc.py
security-checkin/function/logSettings.py
security-checkin/icons/CheckinIcon.ico
security-checkin/icons/Info-icon.png
security-checkin/icons/Py_Logo.png
security-checkin/icons/checkin_app_screenshot.png
security_checkin-0.511.dist-info/LICENSE.md
security_checkin-0.511.dist-info/METADATA
security_checkin-0.511.dist-info/WHEEL
security_checkin-0.511.dist-info/entry_points.txt
security_checkin-0.511.dist-info/top_level.txt
security_checkin-0.511.dist-info/RECORD
