Metadata-Version: 2.1
Name: security-checkin
Version: 0.511
Summary: Keep track of contact with remote teams
Home-page: https://github.com/stevetasticsteve/SecurityCheckin
Author: Stephen Stanley
Author-email: info@realpython.com
License: GPL version 3
Platform: UNKNOWN
Classifier: License :: OSI Approved :: GNU General Public License v3 (GPLv3)
Classifier: Programming Language :: Python :: 3
Requires-Dist: PyQt5
